images/exeter_uni.png
images/gooddatahub-logo.png
images/gooddatahub-logo.svg
images/setsqrd.png
images/taxonomy_example.png
taxonomy4good/__init__.py
taxonomy4good/errors.py
taxonomy4good/sustainabilityItem.py
taxonomy4good/sustainabilityTaxonomy.py
taxonomy4good/taxonomies/china_taxonomy.xlsx
taxonomy4good/taxonomies/en_master_lexicon.xlsx
taxonomy4good/taxonomies/esg_taxonomy.xlsx
taxonomy4good/taxonomies/eu_taxonomy.xlsx
taxonomy4good/taxonomies/ftse_fsgi.xlsx
taxonomy4good/taxonomies/un_sdg_taxonomy.xlsx
taxonomy4good/taxonomies/world_bank_taxonomy.xlsx
taxonomy4good-2.0.0.dist-info/LICENSE
taxonomy4good-2.0.0.dist-info/METADATA
taxonomy4good-2.0.0.dist-info/WHEEL
taxonomy4good-2.0.0.dist-info/top_level.txt
taxonomy4good-2.0.0.dist-info/RECORD
