Metadata-Version: 2.1
Name: taxonomy4good
Version: 2.0.0
Summary: Sustainability lexicon providing both listed and non-listed taxonomies
Home-page: https://taxonomy4good.readthedocs.io/
Author: Hloni Dichabe, Emily Luskind, Zwelakhe Gile, Luvo Gila, Myles Francis, Haroune Aaffoute, Anis Bouhamadouche
Author-email: hloni@gooddatahub.co, emily@gooddatahub.co, zwe@gooddatahub.co, anis@gooddatahub.co
License: MIT
Classifier: Intended Audience :: Developers
Classifier: Intended Audience :: Financial and Insurance Industry
Classifier: Intended Audience :: Legal Industry
Classifier: Intended Audience :: Other Audience
Classifier: License :: OSI Approved :: MIT License
Classifier: Programming Language :: Python
Classifier: Programming Language :: Python :: 3.6
Classifier: Programming Language :: Python :: 3.7
Classifier: Programming Language :: Python :: 3.8
Classifier: Programming Language :: Python :: 3.9
Classifier: Operating System :: OS Independent
License-File: LICENSE
Requires-Dist: numpy
Requires-Dist: pandas
Requires-Dist: xlrd ==1.2.0
Requires-Dist: requests
Requires-Dist: openpyxl
